eclass_mcp_server/__init__.py
eclass_mcp_server/authentication.py
eclass_mcp_server/course_management.py
eclass_mcp_server/html_parsing.py
eclass_mcp_server/server.py
eclass_mcp_server/test/__init__.py
eclass_mcp_server/test/run_all_tests.py
eclass_mcp_server/test/test_courses.py
eclass_mcp_server/test/test_login.py
mseep_eclass_mcp_server-0.1.4.dist-info/licenses/LICENSE
mseep_eclass_mcp_server-0.1.4.dist-info/METADATA
mseep_eclass_mcp_server-0.1.4.dist-info/WHEEL
mseep_eclass_mcp_server-0.1.4.dist-info/entry_points.txt
mseep_eclass_mcp_server-0.1.4.dist-info/top_level.txt
mseep_eclass_mcp_server-0.1.4.dist-info/RECORD
